{
  "data": {
    "date": "20260615",
    "leagues": [
      {
        "ccode": "INT",
        "groupName": "F",
        "id": 894795,
        "internalRank": 0,
        "isGroup": true,
        "localRank": 4,
        "matches": [
          {
            "away": {
              "id": 6719,
              "longName": "Tunisia",
              "name": "Tunisia",
              "score": 1
            },
            "eliminatedTeamId": null,
            "home": {
              "id": 8520,
              "longName": "Sweden",
              "name": "Sweden",
              "score": 5
            },
            "id": 4667784,
            "leagueId": 894795,
            "status": {
              "awarded": false,
              "cancelled": false,
              "finished": true,
              "halfs": {
                "firstHalfStarted": "15.06.2026 04:00:43",
                "secondHalfStarted": "15.06.2026 05:05:46"
              },
              "periodLength": 45,
              "reason": {
                "long": "Full-Time",
                "longKey": "finished",
                "short": "FT",
                "shortKey": "fulltime_short"
              },
              "scoreStr": "5 - 1",
              "started": true,
              "utcTime": "2026-06-15T02:00:00.000Z"
            },
            "statusId": 6,
            "time": "15.06.2026 04:00",
            "timeTS": 1781488800000,
            "tournamentStage": "1"
          }
        ],
        "name": "World Cup Grp. F",
        "parentLeagueId": 77,
        "parentLeagueName": "World Cup",
        "primaryId": 77,
        "simpleLeague": false
      },
      {
        "ccode": "INT",
        "groupName": "H",
        "id": 894797,
        "internalRank": 0,
        "isGroup": true,
        "localRank": 4,
        "matches": [
          {
            "away": {
              "id": 5888,
              "longName": "Cape Verde",
              "name": "Cape Verde",
              "score": 0
            },
            "eliminatedTeamId": null,
            "home": {
              "id": 6720,
              "longName": "Spain",
              "name": "Spain",
              "score": 0
            },
            "id": 4667798,
            "leagueId": 894797,
            "status": {
              "awarded": false,
              "cancelled": false,
              "finished": true,
              "halfs": {
                "firstHalfStarted": "15.06.2026 18:01:09",
                "secondHalfStarted": "15.06.2026 19:06:10"
              },
              "periodLength": 45,
              "reason": {
                "long": "Full-Time",
                "longKey": "finished",
                "short": "FT",
                "shortKey": "fulltime_short"
              },
              "scoreStr": "0 - 0",
              "started": true,
              "utcTime": "2026-06-15T16:00:00.000Z"
            },
            "statusId": 6,
            "time": "15.06.2026 18:00",
            "timeTS": 1781539200000,
            "tournamentStage": "1"
          },
          {
            "away": {
              "id": 5796,
              "longName": "Uruguay",
              "name": "Uruguay",
              "score": 1
            },
            "eliminatedTeamId": null,
            "home": {
              "id": 7795,
              "longName": "Saudi Arabia",
              "name": "Saudi Arabia",
              "score": 1
            },
            "id": 4667799,
            "leagueId": 894797,
            "status": {
              "awarded": false,
              "cancelled": false,
              "finished": true,
              "halfs": {
                "firstHalfStarted": "16.06.2026 00:04:06",
                "secondHalfStarted": "16.06.2026 01:11:01"
              },
              "periodLength": 45,
              "reason": {
                "long": "Full-Time",
                "longKey": "finished",
                "short": "FT",
                "shortKey": "fulltime_short"
              },
              "scoreStr": "1 - 1",
              "started": true,
              "utcTime": "2026-06-15T22:00:00.000Z"
            },
            "statusId": 6,
            "time": "16.06.2026 00:00",
            "timeTS": 1781560800000,
            "tournamentStage": "1"
          }
        ],
        "name": "World Cup Grp. H",
        "parentLeagueId": 77,
        "parentLeagueName": "World Cup",
        "primaryId": 77,
        "simpleLeague": false
      },
      {
        "ccode": "INT",
        "groupName": "G",
        "id": 894796,
        "internalRank": 0,
        "isGroup": true,
        "localRank": 4,
        "matches": [
          {
            "away": {
              "id": 10255,
              "longName": "Egypt",
              "name": "Egypt",
              "score": 1
            },
            "eliminatedTeamId": null,
            "home": {
              "id": 8263,
              "longName": "Belgium",
              "name": "Belgium",
              "score": 1
            },
            "id": 4667790,
            "leagueId": 894796,
            "status": {
              "awarded": false,
              "cancelled": false,
              "finished": true,
              "halfs": {
                "firstHalfStarted": "15.06.2026 21:00:32",
                "secondHalfStarted": "15.06.2026 22:07:32"
              },
              "periodLength": 45,
              "reason": {
                "long": "Full-Time",
                "longKey": "finished",
                "short": "FT",
                "shortKey": "fulltime_short"
              },
              "scoreStr": "1 - 1",
              "started": true,
              "utcTime": "2026-06-15T19:00:00.000Z"
            },
            "statusId": 6,
            "time": "15.06.2026 21:00",
            "timeTS": 1781550000000,
            "tournamentStage": "1"
          }
        ],
        "name": "World Cup Grp. G",
        "parentLeagueId": 77,
        "parentLeagueName": "World Cup",
        "primaryId": 77,
        "simpleLeague": false
      },
      {
        "ccode": "ISL",
        "id": 10226,
        "internalRank": 0,
        "matches": [
          {
            "away": {
              "id": 580181,
              "longName": "Kari",
              "name": "Kari",
              "score": 2
            },
            "eliminatedTeamId": null,
            "home": {
              "id": 4518,
              "longName": "Fjölnir",
              "name": "Fjölnir",
              "score": 2
            },
            "id": 5225911,
            "leagueId": 10226,
            "status": {
              "awarded": false,
              "cancelled": false,
              "finished": true,
              "halfs": {
                "firstHalfStarted": "15.06.2026 21:15:23",
                "secondHalfStarted": "15.06.2026 22:15:56"
              },
              "periodLength": 45,
              "reason": {
                "long": "Full-Time",
                "longKey": "finished",
                "short": "FT",
                "shortKey": "fulltime_short"
              },
              "scoreStr": "2 - 2",
              "started": true,
              "utcTime": "2026-06-15T19:15:00.000Z"
            },
            "statusId": 6,
            "time": "15.06.2026 21:15",
            "timeTS": 1781550900000,
            "tournamentStage": "8"
          },
          {
            "away": {
              "id": 319923,
              "longName": "Throttur Vogar",
              "name": "Throttur Vogar",
              "redCards": 1,
              "score": 1
            },
            "eliminatedTeamId": null,
            "home": {
              "id": 114130,
              "longName": "Selfoss",
              "name": "Selfoss",
              "score": 3
            },
            "id": 5225912,
            "leagueId": 10226,
            "status": {
              "awarded": false,
              "cancelled": false,
              "finished": true,
              "halfs": {
                "firstHalfStarted": "15.06.2026 21:16:26",
                "secondHalfStarted": "15.06.2026 22:17:32"
              },
              "numberOfAwayRedCards": 1,
              "periodLength": 45,
              "reason": {
                "long": "Full-Time",
                "longKey": "finished",
                "short": "FT",
                "shortKey": "fulltime_short"
              },
              "scoreStr": "3 - 1",
              "started": true,
              "utcTime": "2026-06-15T19:15:00.000Z"
            },
            "statusId": 6,
            "time": "15.06.2026 21:15",
            "timeTS": 1781550900000,
            "tournamentStage": "8"
          }
        ],
        "name": "2. Deild",
        "primaryId": 10226,
        "simpleLeague": false
      },
      {
        "ccode": "IRN",
        "id": 9372,
        "internalRank": 8,
        "matches": [
          {
            "away": {
              "id": 101622,
              "longName": "Mes Kerman",
              "name": "Mes Kerman",
              "score": 1
            },
            "eliminatedTeamId": null,
            "home": {
              "id": 955322,
              "longName": "Havadar SC",
              "name": "Havadar SC",
              "score": 1
            },
            "id": 5774213,
            "leagueId": 9372,
            "status": {
              "awarded": false,
              "cancelled": false,
              "finished": true,
              "halfs": {
                "firstHalfStarted": "15.06.2026 16:07:15",
                "secondHalfStarted": "15.06.2026 17:16:50"
              },
              "periodLength": 45,
              "reason": {
                "long": "Full-Time",
                "longKey": "finished",
                "short": "FT",
                "shortKey": "fulltime_short"
              },
              "scoreStr": "1 - 1",
              "started": true,
              "utcTime": "2026-06-15T14:00:00.000Z"
            },
            "statusId": 6,
            "time": "15.06.2026 16:00",
            "timeTS": 1781532000000,
            "tournamentStage": "29"
          },
          {
            "away": {
              "id": 101624,
              "longName": "Sanat Naft Abadan",
              "name": "Sanat-Naft",
              "score": 2
            },
            "eliminatedTeamId": null,
            "home": {
              "id": 1693132,
              "longName": "FC Fard",
              "name": "FC Fard",
              "score": 1
            },
            "id": 5774212,
            "leagueId": 9372,
            "status": {
              "awarded": false,
              "cancelled": false,
              "finished": true,
              "halfs": {
                "firstHalfStarted": "15.06.2026 16:32:28",
                "secondHalfStarted": "15.06.2026 17:37:39"
              },
              "periodLength": 45,
              "reason": {
                "long": "Full-Time",
                "longKey": "finished",
                "short": "FT",
                "shortKey": "fulltime_short"
              },
              "scoreStr": "1 - 2",
              "started": true,
              "utcTime": "2026-06-15T14:30:00.000Z"
            },
            "statusId": 6,
            "time": "15.06.2026 16:30",
            "timeTS": 1781533800000,
            "tournamentStage": "29"
          },
          {
            "away": {
              "id": 392200,
              "longName": "Nassaji Mazandaran FC",
              "name": "Nassaji",
              "score": 1
            },
            "eliminatedTeamId": null,
            "home": {
              "id": 1528916,
              "longName": "Kara Gostar",
              "name": "Kara Gostar",
              "score": 1
            },
            "id": 5774210,
            "leagueId": 9372,
            "status": {
              "awarded": false,
              "cancelled": false,
              "finished": true,
              "halfs": {
                "firstHalfStarted": "15.06.2026 16:36:44",
                "secondHalfStarted": "15.06.2026 17:38:40"
              },
              "periodLength": 45,
              "reason": {
                "long": "Full-Time",
                "longKey": "finished",
                "short": "FT",
                "shortKey": "fulltime_short"
              },
              "scoreStr": "1 - 1",
              "started": true,
              "utcTime": "2026-06-15T14:30:00.000Z"
            },
            "statusId": 6,
            "time": "15.06.2026 16:30",
            "timeTS": 1781533800000,
            "tournamentStage": "29"
          },
          {
            "away": {
              "id": 676588,
              "longName": "Beasat Kermanshah",
              "name": "Beasat Kermanshah",
              "score": 0
            },
            "eliminatedTeamId": null,
            "home": {
              "id": 961464,
              "longName": "Mes Shahr Babak",
              "name": "Mes Shahr Babak",
              "score": 0
            },
            "id": 5774214,
            "leagueId": 9372,
            "status": {
              "awarded": false,
              "cancelled": false,
              "finished": true,
              "halfs": {
                "firstHalfStarted": "15.06.2026 16:33:53",
                "secondHalfStarted": "15.06.2026 17:38:40"
              },
              "periodLength": 45,
              "reason": {
                "long": "Full-Time",
                "longKey": "finished",
                "short": "FT",
                "shortKey": "fulltime_short"
              },
              "scoreStr": "0 - 0",
              "started": true,
              "utcTime": "2026-06-15T14:30:00.000Z"
            },
            "statusId": 6,
            "time": "15.06.2026 16:30",
            "timeTS": 1781533800000,
            "tournamentStage": "29"
          },
          {
            "away": {
              "id": 396142,
              "longName": "Niroye Zamini",
              "name": "Niroye Zamini",
              "score": 3
            },
            "eliminatedTeamId": null,
            "home": {
              "id": 490775,
              "longName": "Naft Gachsaran",
              "name": "Naft Gachsaran",
              "score": 0
            },
            "id": 5774215,
            "leagueId": 9372,
            "status": {
              "awarded": false,
              "cancelled": false,
              "finished": true,
              "halfs": {
                "firstHalfStarted": "15.06.2026 18:03:01",
                "secondHalfStarted": "15.06.2026 19:06:24"
              },
              "periodLength": 45,
              "reason": {
                "long": "Full-Time",
                "longKey": "finished",
                "short": "FT",
                "shortKey": "fulltime_short"
              },
              "scoreStr": "0 - 3",
              "started": true,
              "utcTime": "2026-06-15T16:00:00.000Z"
            },
            "statusId": 6,
            "time": "15.06.2026 18:00",
            "timeTS": 1781539200000,
            "tournamentStage": "29"
          },
          {
            "away": {
              "id": 101615,
              "longName": "Saipa",
              "name": "Saipa",
              "score": 0
            },
            "eliminatedTeamId": null,
            "home": {
              "id": 775750,
              "longName": "Pars Jonoubi Jam",
              "name": "Pars Jonoubi",
              "score": 0
            },
            "id": 5774216,
            "leagueId": 9372,
            "status": {
              "awarded": false,
              "cancelled": false,
              "finished": true,
              "halfs": {
                "firstHalfStarted": "15.06.2026 18:03:03",
                "secondHalfStarted": "15.06.2026 19:06:24"
              },
              "periodLength": 45,
              "reason": {
                "long": "Full-Time",
                "longKey": "finished",
                "short": "FT",
                "shortKey": "fulltime_short"
              },
              "scoreStr": "0 - 0",
              "started": true,
              "utcTime": "2026-06-15T16:00:00.000Z"
            },
            "statusId": 6,
            "time": "15.06.2026 18:00",
            "timeTS": 1781539200000,
            "tournamentStage": "29"
          }
        ],
        "name": "Azadegan League",
        "primaryId": 9372,
        "simpleLeague": false
      },
      {
        "ccode": "ISL",
        "id": 923422,
        "internalRank": 100,
        "matches": [
          {
            "away": {
              "id": 6291,
              "longName": "Fram Reykjavik",
              "name": "Fram Reykjavik",
              "score": 4
            },
            "eliminatedTeamId": null,
            "home": {
              "id": 2165,
              "longName": "KA Akureyri",
              "name": "KA Akureyri",
              "score": 3
            },
            "id": 5225658,
            "leagueId": 923422,
            "status": {
              "awarded": false,
              "cancelled": false,
              "finished": true,
              "halfs": {
                "firstHalfStarted": "15.06.2026 20:01:56",
                "secondHalfStarted": "15.06.2026 21:05:08"
              },
              "periodLength": 45,
              "reason": {
                "long": "Full-Time",
                "longKey": "finished",
                "short": "FT",
                "shortKey": "fulltime_short"
              },
              "scoreStr": "3 - 4",
              "started": true,
              "utcTime": "2026-06-15T18:00:00.000Z"
            },
            "statusId": 6,
            "time": "15.06.2026 20:00",
            "timeTS": 1781546400000,
            "tournamentStage": "10"
          }
        ],
        "name": "Besta deildin",
        "parentLeagueId": 215,
        "primaryId": 215,
        "simpleLeague": false
      },
      {
        "ccode": "ARG",
        "id": 923718,
        "internalRank": 7,
        "matches": [
          {
            "away": {
              "id": 278653,
              "longName": "Defensores de Belgrano de Villa Ramallo",
              "name": "Defensores de Belgrano de Villa Ramallo",
              "score": 0
            },
            "eliminatedTeamId": null,
            "home": {
              "id": 213593,
              "longName": "Sportivo Belgrano",
              "name": "Sportivo Belgrano",
              "score": 1
            },
            "id": 5238312,
            "leagueId": 923718,
            "status": {
              "awarded": false,
              "cancelled": false,
              "finished": true,
              "halfs": {
                "firstHalfStarted": "15.06.2026 23:02:09",
                "secondHalfStarted": "16.06.2026 00:07:26"
              },
              "periodLength": 45,
              "reason": {
                "long": "Full-Time",
                "longKey": "finished",
                "short": "FT",
                "shortKey": "fulltime_short"
              },
              "scoreStr": "1 - 0",
              "started": true,
              "utcTime": "2026-06-15T21:00:00.000Z"
            },
            "statusId": 6,
            "time": "15.06.2026 23:00",
            "timeTS": 1781557200000,
            "tournamentStage": "13"
          }
        ],
        "name": "Federal A Zona A",
        "parentLeagueId": 9213,
        "primaryId": 9213,
        "simpleLeague": false
      },
      {
        "ccode": "NOR",
        "groupName": "4",
        "id": 919795,
        "internalRank": 0,
        "isGroup": true,
        "matches": [
          {
            "away": {
              "id": 9845,
              "longName": "Odds Ballklubb 2",
              "name": "Odd 2",
              "score": 2
            },
            "eliminatedTeamId": null,
            "home": {
              "id": 4231,
              "longName": "Staal Jørpeland",
              "name": "Staal Jørpeland",
              "score": 5
            },
            "id": 5144319,
            "leagueId": 919795,
            "status": {
              "awarded": false,
              "cancelled": false,
              "finished": true,
              "halfs": {
                "firstHalfStarted": "15.06.2026 18:00:40",
                "secondHalfStarted": "15.06.2026 19:05:44"
              },
              "periodLength": 45,
              "reason": {
                "long": "Full-Time",
                "longKey": "finished",
                "short": "FT",
                "shortKey": "fulltime_short"
              },
              "scoreStr": "5 - 2",
              "started": true,
              "utcTime": "2026-06-15T16:00:00.000Z"
            },
            "statusId": 6,
            "time": "15.06.2026 18:00",
            "timeTS": 1781539200000,
            "tournamentStage": "10"
          },
          {
            "away": {
              "id": 9844,
              "longName": "Stabæk 2",
              "name": "Stabæk 2",
              "score": 2
            },
            "eliminatedTeamId": null,
            "home": {
              "id": 4216,
              "longName": "Våg",
              "name": "Våg",
              "score": 3
            },
            "id": 5144320,
            "leagueId": 919795,
            "status": {
              "awarded": false,
              "cancelled": false,
              "finished": true,
              "halfs": {
                "firstHalfStarted": "15.06.2026 18:02:29",
                "secondHalfStarted": "15.06.2026 19:06:24"
              },
              "periodLength": 45,
              "reason": {
                "long": "Full-Time",
                "longKey": "finished",
                "short": "FT",
                "shortKey": "fulltime_short"
              },
              "scoreStr": "3 - 2",
              "started": true,
              "utcTime": "2026-06-15T16:00:00.000Z"
            },
            "statusId": 6,
            "time": "15.06.2026 18:00",
            "timeTS": 1781539200000,
            "tournamentStage": "10"
          }
        ],
        "name": "3. Divisjon Avd. 4",
        "parentLeagueId": 205,
        "parentLeagueName": "Norsk Tipping-ligaen",
        "primaryId": 205,
        "simpleLeague": false
      },
      {
        "ccode": "NOR",
        "groupName": "6",
        "id": 919797,
        "internalRank": 0,
        "isGroup": true,
        "matches": [
          {
            "away": {
              "id": 4244,
              "longName": "Lyn 2",
              "name": "Lyn 2",
              "score": 1
            },
            "eliminatedTeamId": null,
            "home": {
              "id": 4703,
              "longName": "Fram Larvik",
              "name": "Fram Larvik",
              "score": 0
            },
            "id": 5144695,
            "leagueId": 919797,
            "status": {
              "awarded": false,
              "cancelled": false,
              "finished": true,
              "halfs": {
                "firstHalfStarted": "15.06.2026 18:01:43",
                "secondHalfStarted": "15.06.2026 19:03:14"
              },
              "periodLength": 45,
              "reason": {
                "long": "Full-Time",
                "longKey": "finished",
                "short": "FT",
                "shortKey": "fulltime_short"
              },
              "scoreStr": "0 - 1",
              "started": true,
              "utcTime": "2026-06-15T16:00:00.000Z"
            },
            "statusId": 6,
            "time": "15.06.2026 18:00",
            "timeTS": 1781539200000,
            "tournamentStage": "10"
          }
        ],
        "name": "3. Divisjon Avd. 6",
        "parentLeagueId": 205,
        "parentLeagueName": "Norsk Tipping-ligaen",
        "primaryId": 205,
        "simpleLeague": false
      },
      {
        "ccode": "NOR",
        "groupName": "2",
        "id": 919793,
        "internalRank": 0,
        "isGroup": true,
        "matches": [
          {
            "away": {
              "id": 4332,
              "longName": "Kvik",
              "name": "Kvik",
              "score": 1
            },
            "eliminatedTeamId": null,
            "home": {
              "id": 46922,
              "longName": "Ranheim 2",
              "name": "Ranheim 2",
              "score": 1
            },
            "id": 5143955,
            "leagueId": 919793,
            "status": {
              "awarded": false,
              "cancelled": false,
              "finished": true,
              "halfs": {
                "firstHalfStarted": "15.06.2026 19:00:14",
                "secondHalfStarted": "15.06.2026 20:00:44"
              },
              "periodLength": 45,
              "reason": {
                "long": "Full-Time",
                "longKey": "finished",
                "short": "FT",
                "shortKey": "fulltime_short"
              },
              "scoreStr": "1 - 1",
              "started": true,
              "utcTime": "2026-06-15T17:00:00.000Z"
            },
            "statusId": 6,
            "time": "15.06.2026 19:00",
            "timeTS": 1781542800000,
            "tournamentStage": "10"
          }
        ],
        "name": "3. Divisjon Avd. 2",
        "parentLeagueId": 205,
        "parentLeagueName": "Norsk Tipping-ligaen",
        "primaryId": 205,
        "simpleLeague": false
      },
      {
        "ccode": "NOR",
        "groupName": "3",
        "id": 919794,
        "internalRank": 0,
        "isGroup": true,
        "matches": [
          {
            "away": {
              "id": 7864,
              "longName": "Stord",
              "name": "Stord",
              "score": 2
            },
            "eliminatedTeamId": null,
            "home": {
              "id": 246204,
              "longName": "Åsane 2",
              "name": "Åsane 2",
              "score": 1
            },
            "id": 5144136,
            "leagueId": 919794,
            "status": {
              "awarded": false,
              "cancelled": false,
              "finished": true,
              "halfs": {
                "firstHalfStarted": "15.06.2026 19:00:45",
                "secondHalfStarted": "15.06.2026 20:00:44"
              },
              "periodLength": 45,
              "reason": {
                "long": "Full-Time",
                "longKey": "finished",
                "short": "FT",
                "shortKey": "fulltime_short"
              },
              "scoreStr": "1 - 2",
              "started": true,
              "utcTime": "2026-06-15T17:00:00.000Z"
            },
            "statusId": 6,
            "time": "15.06.2026 19:00",
            "timeTS": 1781542800000,
            "tournamentStage": "10"
          }
        ],
        "name": "3. Divisjon Avd. 3",
        "parentLeagueId": 205,
        "parentLeagueName": "Norsk Tipping-ligaen",
        "primaryId": 205,
        "simpleLeague": false
      },
      {
        "ccode": "NOR",
        "groupName": "5",
        "id": 919796,
        "internalRank": 0,
        "isGroup": true,
        "matches": [
          {
            "away": {
              "id": 2536,
              "longName": "Skjetten",
              "name": "Skjetten",
              "score": 5
            },
            "eliminatedTeamId": null,
            "home": {
              "id": 4254,
              "longName": "Kongsvinger 2",
              "name": "Kongsvinger 2",
              "score": 3
            },
            "id": 5144502,
            "leagueId": 919796,
            "status": {
              "awarded": false,
              "cancelled": false,
              "finished": true,
              "halfs": {
                "firstHalfStarted": "15.06.2026 20:01:18",
                "secondHalfStarted": "15.06.2026 21:04:05"
              },
              "periodLength": 45,
              "reason": {
                "long": "Full-Time",
                "longKey": "finished",
                "short": "FT",
                "shortKey": "fulltime_short"
              },
              "scoreStr": "3 - 5",
              "started": true,
              "utcTime": "2026-06-15T18:00:00.000Z"
            },
            "statusId": 6,
            "time": "15.06.2026 20:00",
            "timeTS": 1781546400000,
            "tournamentStage": "10"
          }
        ],
        "name": "3. Divisjon Avd. 5",
        "parentLeagueId": 205,
        "parentLeagueName": "Norsk Tipping-ligaen",
        "primaryId": 205,
        "simpleLeague": false
      },
      {
        "ccode": "TAN",
        "id": 9066,
        "internalRank": 0,
        "matches": [
          {
            "away": {
              "id": 287669,
              "longName": "Coastal Union",
              "name": "Coastal Union",
              "score": 3
            },
            "eliminatedTeamId": null,
            "home": {
              "id": 1045551,
              "longName": "Kinondoni MC",
              "name": "Kinondoni MC",
              "score": 1
            },
            "id": 4951105,
            "leagueId": 9066,
            "status": {
              "awarded": false,
              "cancelled": false,
              "finished": true,
              "halfs": {
                "firstHalfStarted": "15.06.2026 15:01:08",
                "secondHalfStarted": "15.06.2026 16:03:00"
              },
              "periodLength": 45,
              "reason": {
                "long": "Full-Time",
                "longKey": "finished",
                "short": "FT",
                "shortKey": "fulltime_short"
              },
              "scoreStr": "1 - 3",
              "started": true,
              "utcTime": "2026-06-15T13:00:00.000Z"
            },
            "statusId": 6,
            "time": "15.06.2026 15:00",
            "timeTS": 1781528400000,
            "tournamentStage": "27"
          }
        ],
        "name": "Premier League",
        "primaryId": 9066,
        "simpleLeague": false
      },
      {
        "ccode": "SWE",
        "id": 168,
        "internalRank": 8,
        "matches": [
          {
            "away": {
              "id": 8641,
              "longName": "Östers IF",
              "name": "Östers IF",
              "score": 4
            },
            "eliminatedTeamId": null,
            "home": {
              "id": 8359,
              "longName": "GIF Sundsvall",
              "name": "GIF Sundsvall",
              "score": 0
            },
            "id": 5125539,
            "leagueId": 168,
            "status": {
              "awarded": false,
              "cancelled": false,
              "finished": true,
              "halfs": {
                "firstHalfStarted": "15.06.2026 19:00:45",
                "secondHalfStarted": "15.06.2026 20:01:18"
              },
              "periodLength": 45,
              "reason": {
                "long": "Full-Time",
                "longKey": "finished",
                "short": "FT",
                "shortKey": "fulltime_short"
              },
              "scoreStr": "0 - 4",
              "started": true,
              "utcTime": "2026-06-15T17:00:00.000Z"
            },
            "statusId": 6,
            "time": "15.06.2026 19:00",
            "timeTS": 1781542800000,
            "tournamentStage": "12"
          },
          {
            "away": {
              "id": 6692,
              "longName": "Varbergs BoIS FC",
              "name": "Varbergs BoIS FC",
              "score": 0
            },
            "eliminatedTeamId": null,
            "home": {
              "id": 8449,
              "longName": "IFK Norrköping",
              "name": "IFK Norrköping",
              "score": 2
            },
            "id": 5125537,
            "leagueId": 168,
            "status": {
              "awarded": false,
              "cancelled": false,
              "finished": true,
              "halfs": {
                "firstHalfStarted": "15.06.2026 19:05:44",
                "secondHalfStarted": "15.06.2026 20:06:24"
              },
              "periodLength": 45,
              "reason": {
                "long": "Full-Time",
                "longKey": "finished",
                "short": "FT",
                "shortKey": "fulltime_short"
              },
              "scoreStr": "2 - 0",
              "started": true,
              "utcTime": "2026-06-15T17:05:00.000Z"
            },
            "statusId": 6,
            "time": "15.06.2026 19:05",
            "timeTS": 1781543100000,
            "tournamentStage": "12"
          }
        ],
        "name": "Superettan",
        "primaryId": 168,
        "simpleLeague": false
      },
      {
        "ccode": "FIN",
        "id": 920261,
        "internalRank": 9,
        "matches": [
          {
            "away": {
              "id": 7870,
              "longName": "Haka",
              "name": "Haka",
              "score": 2
            },
            "eliminatedTeamId": null,
            "home": {
              "id": 741816,
              "longName": "SJK Akatemia",
              "name": "SJK Akatemia",
              "redCards": 1,
              "score": 0
            },
            "id": 5163710,
            "leagueId": 920261,
            "status": {
              "awarded": false,
              "cancelled": false,
              "finished": true,
              "halfs": {
                "firstHalfStarted": "15.06.2026 17:32:09",
                "secondHalfStarted": "15.06.2026 18:39:29"
              },
              "numberOfHomeRedCards": 1,
              "periodLength": 45,
              "reason": {
                "long": "Full-Time",
                "longKey": "finished",
                "short": "FT",
                "shortKey": "fulltime_short"
              },
              "scoreStr": "0 - 2",
              "started": true,
              "utcTime": "2026-06-15T15:30:00.000Z"
            },
            "statusId": 6,
            "time": "15.06.2026 17:30",
            "timeTS": 1781537400000,
            "tournamentStage": "1"
          }
        ],
        "name": "Ykkosliiga",
        "parentLeagueId": 251,
        "primaryId": 251,
        "simpleLeague": false
      },
      {
        "ccode": "BOL",
        "id": 144,
        "internalRank": 0,
        "matches": [
          {
            "away": {
              "id": 2527,
              "longName": "The Strongest",
              "name": "The Strongest",
              "score": 0
            },
            "eliminatedTeamId": null,
            "home": {
              "id": 49678,
              "longName": "Blooming",
              "name": "Blooming",
              "score": 0
            },
            "id": 1000011163,
            "leagueId": 144,
            "status": {
              "cancelled": true,
              "finished": false,
              "halfs": {
                "firstHalfStarted": "15.06.2026 02:30:00"
              },
              "periodLength": 45,
              "reason": {
                "long": "Postponed",
                "longKey": "postponed",
                "short": "PP",
                "shortKey": "postponed_short"
              },
              "started": false,
              "utcTime": "2026-06-15T00:30:00.000Z"
            },
            "statusId": 5,
            "time": "15.06.2026 02:30",
            "timeTS": 1781483400000,
            "tournamentStage": "11"
          },
          {
            "away": {
              "id": 114830,
              "longName": "Guabira",
              "name": "Guabira",
              "score": 0
            },
            "eliminatedTeamId": null,
            "home": {
              "id": 5983,
              "longName": "Bolivar",
              "name": "Bolivar",
              "score": 0
            },
            "id": 1000010878,
            "leagueId": 144,
            "status": {
              "cancelled": true,
              "finished": false,
              "halfs": {
                "firstHalfStarted": "16.06.2026 01:00:00"
              },
              "periodLength": 45,
              "reason": {
                "long": "Postponed",
                "longKey": "postponed",
                "short": "PP",
                "shortKey": "postponed_short"
              },
              "started": false,
              "utcTime": "2026-06-15T23:00:00.000Z"
            },
            "statusId": 5,
            "time": "16.06.2026 01:00",
            "timeTS": 1781564400000,
            "tournamentStage": "9"
          }
        ],
        "name": "Primera División",
        "primaryId": 144,
        "simpleLeague": false
      },
      {
        "ccode": "BRA",
        "id": 8971,
        "internalRank": 0,
        "matches": [
          {
            "away": {
              "id": 197781,
              "longName": "Maranhao",
              "name": "Maranhao",
              "score": 0
            },
            "eliminatedTeamId": null,
            "home": {
              "id": 509487,
              "longName": "Maringa FC",
              "name": "Maringa FC",
              "score": 0
            },
            "id": 1000009437,
            "leagueId": 8971,
            "status": {
              "awarded": false,
              "cancelled": false,
              "finished": true,
              "halfs": {
                "firstHalfStarted": "16.06.2026 00:33:19",
                "secondHalfStarted": "16.06.2026 01:43:29"
              },
              "periodLength": 45,
              "reason": {
                "long": "Full-Time",
                "longKey": "finished",
                "short": "FT",
                "shortKey": "fulltime_short"
              },
              "scoreStr": "0 - 0",
              "started": true,
              "utcTime": "2026-06-15T22:30:00.000Z"
            },
            "statusId": 6,
            "time": "16.06.2026 00:30",
            "timeTS": 1781562600000,
            "tournamentStage": "10"
          },
          {
            "away": {
              "id": 1320333,
              "longName": "Barra FC",
              "name": "Barra FC",
              "score": 0
            },
            "eliminatedTeamId": null,
            "home": {
              "id": 581832,
              "longName": "Ferroviaria",
              "name": "Ferroviaria",
              "score": 1
            },
            "id": 1000009431,
            "leagueId": 8971,
            "status": {
              "awarded": false,
              "cancelled": false,
              "finished": true,
              "halfs": {
                "firstHalfStarted": "16.06.2026 01:29:35",
                "secondHalfStarted": "16.06.2026 02:34:38"
              },
              "periodLength": 45,
              "reason": {
                "long": "Full-Time",
                "longKey": "finished",
                "short": "FT",
                "shortKey": "fulltime_short"
              },
              "scoreStr": "1 - 0",
              "started": true,
              "utcTime": "2026-06-15T23:30:00.000Z"
            },
            "statusId": 6,
            "time": "16.06.2026 01:30",
            "timeTS": 1781566200000,
            "tournamentStage": "10"
          },
          {
            "away": {
              "id": 197792,
              "longName": "Botafogo PB",
              "name": "Botafogo PB",
              "redCards": 1,
              "score": 1
            },
            "eliminatedTeamId": null,
            "home": {
              "id": 197885,
              "longName": "Ypiranga RS",
              "name": "Ypiranga RS",
              "score": 1
            },
            "id": 1000009438,
            "leagueId": 8971,
            "status": {
              "awarded": false,
              "cancelled": false,
              "finished": true,
              "halfs": {
                "firstHalfStarted": "16.06.2026 01:32:01",
                "secondHalfStarted": "16.06.2026 02:35:35"
              },
              "numberOfAwayRedCards": 1,
              "periodLength": 45,
              "reason": {
                "long": "Full-Time",
                "longKey": "finished",
                "short": "FT",
                "shortKey": "fulltime_short"
              },
              "scoreStr": "1 - 1",
              "started": true,
              "utcTime": "2026-06-15T23:30:00.000Z"
            },
            "statusId": 6,
            "time": "16.06.2026 01:30",
            "timeTS": 1781566200000,
            "tournamentStage": "10"
          }
        ],
        "name": "Serie C",
        "primaryId": 8971,
        "simpleLeague": false
      }
    ]
  },
  "status": "success"
}